simpleval/__main__.py
simpleval/cli_args.py
simpleval/consts.py
simpleval/exceptions.py
simpleval/logger.py
simpleval/main.py
simpleval/validations.py
simpleval/commands/__init__.py
simpleval/commands/judge_explorer_command.py
simpleval/commands/list_models_command.py
simpleval/commands/litellm_models_explorer_command.py
simpleval/commands/metrics_explorer_command.py
simpleval/commands/run_command.py
simpleval/commands/init_command/base_init.py
simpleval/commands/init_command/consts.py
simpleval/commands/init_command/init_command.py
simpleval/commands/init_command/init_from_template.py
simpleval/commands/init_command/init_from_template_command.py
simpleval/commands/init_command/init_interactive.py
simpleval/commands/init_command/user_functions.py
simpleval/commands/reporting/__init__.py
simpleval/commands/reporting/utils.py
simpleval/commands/reporting/compare/__init__.py
simpleval/commands/reporting/compare/common.py
simpleval/commands/reporting/compare/compare_command.py
simpleval/commands/reporting/compare/compare_console.py
simpleval/commands/reporting/compare/compare_html2/__init__.py
simpleval/commands/reporting/compare/compare_html2/compare_html2.py
simpleval/commands/reporting/compare/compare_html2/compare_report_template.html
simpleval/commands/reporting/eval/__init__.py
simpleval/commands/reporting/eval/console_report.py
simpleval/commands/reporting/eval/eval_report.py
simpleval/commands/reporting/eval/eval_report_command.py
simpleval/commands/reporting/eval/eval_report_file_command.py
simpleval/commands/reporting/eval/html_common.py
simpleval/commands/reporting/eval/html2/__init__.py
simpleval/commands/reporting/eval/html2/html2_report.py
simpleval/commands/reporting/eval/html2/llm_eval_report_template.html
simpleval/commands/reporting/summarize/llm_summary_report_template.html
simpleval/commands/reporting/summarize/summarize_command.py
simpleval/commands/reporting/summarize/summarize_html.py
simpleval/eval_sets/detect_user_action/README.md
simpleval-1.1.1.dist-info/METADATA
simpleval-1.1.1.dist-info/WHEEL
simpleval-1.1.1.dist-info/entry_points.txt
simpleval-1.1.1.dist-info/licenses/LICENSE
simpleval-1.1.1.dist-info/licenses/NOTICES.txt
simpleval-1.1.1.dist-info/RECORD
