Metadata-Version: 2.4
Name: simpleval
Version: 1.1.1
Summary: Simple Evaluation Framework for LLM use cases
Project-URL: Repository, https://github.com/cyberark/simple-llm-eval
Author-email: Roy Ben Yosef <roy.benyosef@cyberark.com>
License-File: LICENSE
License-File: NOTICES.txt
Classifier: Programming Language :: Python :: 3
Classifier: Programming Language :: Python :: 3.11
Classifier: Programming Language :: Python :: 3.12
Classifier: Programming Language :: Python :: 3.13
Requires-Python: >=3.11
Requires-Dist: boto3<2,>=1.42.25
Requires-Dist: click<9,>=8.3.1
Requires-Dist: colorama<0.5,>=0.4.6
Requires-Dist: google-genai<2,>=1.57.0
Requires-Dist: httpcore<2,>=1.0.9
Requires-Dist: inquirerpy<0.4,>=0.3.4
Requires-Dist: litellm>=1.80.13
Requires-Dist: pydantic<3,>=2.12.5
Requires-Dist: tabulate<0.10,>=0.9.0
Requires-Dist: tenacity<10,>=9.1.2
Requires-Dist: tqdm<5,>=4.67.1
Requires-Dist: urllib3>=2.6.3
